coreir.libs/libcoreirsim-f531ba2f.so
coreir.libs/libverilogAST-55b64733.so
coreir-2.0.156.data/scripts/coreir
coreir/libcoreir-aetherlinglib.so
coreir/type_gen.py
coreir/__init__.py
coreir/generator.py
coreir/libcoreir-rtlil.so
coreir/libcoreir-c.so
coreir/libcoreir-commonlib.so
coreir/libverilogAST.so
coreir/wireable.py
coreir/simulator.py
coreir/libcoreir-ice40.so
coreir/global_value.py
coreir/libcoreir-float.so
coreir/util.py
coreir/namespace.py
coreir/libcoreir-float_CW.so
coreir/base.py
coreir/lib.py
coreir/coreir
coreir/module.py
coreir/type.py
coreir/context.py
coreir/libcoreir-float_DW.so
coreir/libcoreirsim-c.so
coreir-2.0.156.dist-info/LICENSE.txt
coreir-2.0.156.dist-info/RECORD
coreir-2.0.156.dist-info/METADATA
coreir-2.0.156.dist-info/top_level.txt
coreir-2.0.156.dist-info/WHEEL
