Metadata-Version: 2.1
Name: coreir
Version: 2.0.156
Summary: Python bindings for CoreIR
Home-page: https://github.com/leonardt/pycoreir
Author: Leonard Truong
Author-email: lenny@cs.stanford.edu
License: BSD License
Platform: UNKNOWN
License-File: LICENSE.txt
Requires-Dist: hwtypes
